permalint/__init__.py
permalint-0.1.15.dist-info/METADATA
permalint-0.1.15.dist-info/WHEEL
permalint-0.1.15.dist-info/RECORD
