Metadata-Version: 2.4
Name: permalint
Version: 0.1.15
Summary: Lint URLs
Project-URL: Homepage, https://github.com/sanchitram/permalint
Project-URL: Repository, https://github.com/sanchitram/permalint
Project-URL: Source, https://github.com/sanchitram/permalint
Author-email: Sanchit Ram Arvind <sanchitram@gmail.com>
Requires-Python: >=3.9
Requires-Dist: ruff~=0.0
Requires-Dist: tldextract>=5.3.0
